thns/__about__.py
thns/__init__.py
thns/__main__.py
thns-0.0.5.dist-info/METADATA
thns-0.0.5.dist-info/WHEEL
thns-0.0.5.dist-info/entry_points.txt
thns-0.0.5.dist-info/licenses/LICENSE
thns-0.0.5.dist-info/RECORD
