Metadata-Version: 2.1
Name: thns
Version: 0.0.5
Summary: Get Telegram notifications when requests are being made to your web server
Project-URL: Bug Reports, https://gitlab.com/0bs1d1an/thns/issues
Project-URL: Homepage, https://gitlab.com/0bs1d1an/thns
Project-URL: Source, https://gitlab.com/0bs1d1an/thns/
Author-email: "Guido Kroon (@0bs1d1an)" <gkroon@maelstrom.ninja>
License-Expression: BSD-3-Clause
License-File: LICENSE
Classifier: Development Status :: 4 - Beta
Classifier: Intended Audience :: Information Technology
Classifier: Intended Audience :: System Administrators
Classifier: License :: OSI Approved :: GNU General Public License v3 (GPLv3)
Classifier: Programming Language :: Python
Classifier: Programming Language :: Python :: 3.6
Classifier: Programming Language :: Python :: 3.7
Classifier: Programming Language :: Python :: 3.8
Classifier: Programming Language :: Python :: 3.9
Classifier: Programming Language :: Python :: 3.10
Classifier: Programming Language :: Python :: 3.11
Classifier: Programming Language :: Python :: Implementation :: CPython
Classifier: Programming Language :: Python :: Implementation :: PyPy
Classifier: Topic :: Security
Requires-Python: >=3.6
